dash_prefix/__init__.py
dash_prefix/_version.py
dash_prefix/component_id.py
dash_prefix/dash_prefix.py
dash_prefix-0.0.4.dist-info/LICENSE
dash_prefix-0.0.4.dist-info/METADATA
dash_prefix-0.0.4.dist-info/WHEEL
dash_prefix-0.0.4.dist-info/top_level.txt
dash_prefix-0.0.4.dist-info/RECORD
