Metadata-Version: 2.1
Name: dash-prefix
Version: 0.0.4
Summary: Dash library for managing component IDs
Home-page: https://github.com/stevej2608/dash-prefix
Author: Steve Jones
Author-email: jonesst608@gmail.com
License: MIT
Platform: UNKNOWN
Classifier: Development Status :: 2 - Pre-Alpha
Classifier: License :: OSI Approved :: MIT License
Classifier: Programming Language :: Python
Classifier: Programming Language :: Python :: 3.6
Classifier: Programming Language :: Python :: 3.7
Requires-Dist: dash (>=2.1.0)
